README.txt
setup.cfg
setup.py
collective/__init__.py
collective.siterss.egg-info/PKG-INFO
collective.siterss.egg-info/SOURCES.txt
collective.siterss.egg-info/dependency_links.txt
collective.siterss.egg-info/entry_points.txt
collective.siterss.egg-info/namespace_packages.txt
collective.siterss.egg-info/not-zip-safe
collective.siterss.egg-info/requires.txt
collective.siterss.egg-info/top_level.txt
collective/siterss/__init__.py
collective/siterss/configure.zcml
collective/siterss/interfaces.py
collective/siterss/rebuild_i18n.sh
collective/siterss/setuphandlers.py
collective/siterss/tests.py
collective/siterss/browser/__init__.py
collective/siterss/browser/catalog_vocabulary.py
collective/siterss/browser/configure.zcml
collective/siterss/browser/controlpanel.py
collective/siterss/browser/rsslinks.pt
collective/siterss/browser/viewlets.py
collective/siterss/locales/collective.siterss.pot
collective/siterss/locales/en/LC_MESSAGES/collective.siterss.po
collective/siterss/locales/nl/LC_MESSAGES/collective.siterss.po
collective/siterss/profiles/default/actionicons.xml
collective/siterss/profiles/default/browserlayer.xml
collective/siterss/profiles/default/controlpanel.xml
collective/siterss/profiles/default/metadata.xml
collective/siterss/profiles/default/propertiestool.xml
collective/siterss/profiles/default/siterss-install.txt
collective/siterss/profiles/default/viewlets.xml
collective/siterss/profiles/uninstall/import_steps.xml
collective/siterss/profiles/uninstall/siterss-uninstall.txt
collective/siterss/profiles/uninstall/viewlets.xml
docs/HISTORY.txt
docs/INSTALL.txt
docs/LICENSE.GPL
docs/LICENSE.txt