Metadata-Version: 1.0
Name: collective.siterss
Version: 0.4
Summary: Use any Smart Folder as default RSS feed of Plone instance
Home-page: http://svn.plone.org/svn/collective/collective.siterss
Author: Radim Novotny
Author-email: novotny.radim@gmail.com
License: GPL
Keywords: plone rss
Platform: UNKNOWN
Classifier: Framework :: Plone
Classifier: Programming Language :: Python
Classifier: Topic :: Software Development :: Libraries :: Python Modules
